{"cameraMode":{"drawMode":0,"name":"Shaded","section":"Shading Mode"},"sceneLighting":true,"audioPlay":false,"sceneViewState":{"m_AlwaysRefresh":false,"showFog":true,"showSkybox":true,"showFlares":true,"showImageEffects":true,"showParticleSystems":true,"showVisualEffectGraphs":true,"m_FxEnabled":true},"in2DMode":false,"pivot":{"x":387.0509033203125,"y":229.66049194335938,"z":298.22210693359377},"rotation":{"x":-0.03480095416307449,"y":-0.009896528907120228,"z":0.00034502020571380854,"w":-0.999347984790802},"size":379.5320739746094,"orthographic":false}